flake8_global_variables/__init__.py
flake8_global_variables-0.1.2.dist-info/entry_points.txt
flake8_global_variables-0.1.2.dist-info/LICENSE
flake8_global_variables-0.1.2.dist-info/WHEEL
flake8_global_variables-0.1.2.dist-info/METADATA
flake8_global_variables-0.1.2.dist-info/RECORD
